
  <model>
    <instance>
        <pcimne_register xmlns:jr="http://openrosa.org/javarosa" xmlns:orx="http://openrosa.org/xforms" id="pcimne_register" prefix="J1!pcimne_register!" delimiter="#" version="2024-07-04  11-49">
          <inputs>
            <meta>
              <location>
                <lat/>
                <long/>
                <error/>
                <message/>
              </location>
            </meta>
            <source>user</source>
            <source_id/>
            <user>
              <contact_id/>
              <name/>
              <phone/>
              <role/>
              <external_id/>
            </user>
            <contact>
              <_id/>
              <name/>
              <sex/>
              <date_of_birth/>
              <external_id/>
              <parent>
                <_id/>
                <name/>
                <external_id/>
                <parent>
                  <_id/>
                  <parent>
                    <_id/>
                    <parent>
                      <_id/>
                      <parent>
                        <_id/>
                        <parent>
                          <_id/>
                          <parent>
                            <_id/>
                            <parent>
                              <_id/>
                            </parent>
                          </parent>
                        </parent>
                      </parent>
                    </parent>
                  </parent>
                  <contact>
                    <_id/>
                    <name/>
                  </contact>
                </parent>
              </parent>
            </contact>
          </inputs>
          <user_id/>
          <user_uid/>
          <user_phone/>
          <user_phone_to_show/>
          <patient_id/>
          <patient_name/>
          <patient_name_to_show/>
          <patient_external_id/>
          <patient_date_of_birth/>
          <patient_age_in_years/>
          <patient_age_in_months/>
          <patient_age_in_days/>
          <patient_age_display_fr/>
          <patient_age_display_en/>
          <patient_sex/>
          <patient_sex_en/>
          <patient_sex_fr/>
          <patient_family_name/>
          <patient_family_external_id/>
          <visited_contact_uuid/>
          <household_id/>
          <household_uid/>
          <village_secteur_id/>
          <village_secteur_uid/>
          <district_quartier_id/>
          <district_quartier_uid/>
          <hospital_id/>
          <hospital_uid/>
          <commune_id/>
          <commune_uid/>
          <prefecture_id/>
          <prefecture_uid/>
          <region_id/>
          <region_uid/>
          <country_id/>
          <country_uid/>
          <promptitude/>
          <has_initial_danger_signs/>
          <is_danger_signs_referral/>
          <has_fever/>
          <has_malaria/>
          <is_fever_referal/>
          <has_cough_cold/>
          <has_pneumonia/>
          <has_normal_respiratory_rate/>
          <is_cough_cold_referal/>
          <has_diarrhea/>
          <is_diarrhea_referal/>
          <has_malnutrition/>
          <is_malnutrition_referal/>
          <has_afp/>
          <has_other_disease_problem/>
          <other_diseases/>
          <temperature/>
          <rdt_given/>
          <rdt_result/>
          <unable_drink_breastfeed/>
          <vomits_everything/>
          <convulsions/>
          <sleepy_unconscious/>
          <has_stiff_neck/>
          <has_bulging_fontanelle/>
          <breathing_difficulty/>
          <cough_more_than_14days/>
          <subcostal_indrawing/>
          <wheezing/>
          <bloody_diarrhea/>
          <diarrhea_more_than_14_days/>
          <blood_in_stool/>
          <restless/>
          <drinks_hungrily/>
          <sunken_eyes/>
          <has_edema/>
          <has_serious_malaria/>
          <is_principal_referal/>
          <has_health_problem/>
          <is_referred/>
          <cta_quantity/>
          <amoxicillin_250mg_quantity/>
          <amoxicillin_500mg_quantity/>
          <paracetamol_250mg_quantity/>
          <paracetamol_500mg_quantity/>
          <mebendazole_250mg_quantity/>
          <mebendazole_500mg_quantity/>
          <ors_quantity/>
          <zinc_quantity/>
          <vitamin_a_quantity/>
          <tetracycline_ointment_quantity/>
          <referal_health_center/>
          <has_pre_reference_treatments/>
          <next_visit/>
          <c_time_of_consultation>
            <c_promptitude/>
          </c_time_of_consultation>
          <c_danger_sign_control>
            <c_unable_drink_breastfeed/>
            <c_vomits_everything/>
            <c_convulsions/>
            <c_sleepy_unconscious/>
          </c_danger_sign_control>
          <c_fever>
            <c_has_fever/>
            <c_has_stiff_neck/>
            <c_has_bulging_fontanelle/>
            <c_temperature_taken/>
            <c_temperature/>
            <c_rdt_given/>
            <c_rdt_result/>
            <c_serious_malaria/>
          </c_fever>
          <c_cough_cold>
            <c_has_cough_cold/>
            <c_breathing_difficulty/>
            <c_cough_more_than_14days/>
            <c_subcostal_indrawing/>
            <c_wheezing/>
            <c_breath_timer/>
            <c_respiratory_rate_per_minute/>
            <c_respiratory_rate_info/>
            <c_respiratory_rate_note/>
            <c_pneumony/>
          </c_cough_cold>
          <c_diarrhea>
            <c_has_diarrhea/>
            <c_bloody_diarrhea/>
            <c_diarrhea_more_than_14_days/>
            <c_blood_in_stool/>
            <c_restless/>
            <c_drinks_hungrily/>
            <c_sunken_eyes/>
          </c_diarrhea>
          <c_nutritional>
            <c_upper_arm_circumference/>
            <c_upper_arm_circumference_color/>
            <c_pb_less_than_12_5_cm/>
            <c_pb_greater_than_12_5_cm/>
            <c_has_edema/>
          </c_nutritional>
          <c_other_diseases>
            <c_has_afp/>
            <c_has_other_disease_problem/>
            <c_other_diseases_given/>
          </c_other_diseases>
          <child_vaccination>
            <c_has_health_record/>
            <vaccination_followup db-doc="true">
              <form/>
              <type/>
              <content_type/>
              <from/>
              <contact>
                <_id/>
                <parent>
                  <_id/>
                  <parent>
                    <_id/>
                    <parent>
                      <_id/>
                      <parent>
                        <_id/>
                        <parent>
                          <_id/>
                          <parent>
                            <_id/>
                            <parent>
                              <_id/>
                            </parent>
                          </parent>
                        </parent>
                      </parent>
                    </parent>
                  </parent>
                </parent>
              </contact>
              <fields>
                <inputs>
                  <source/>
                  <source_id/>
                  <contact>
                    <_id/>
                    <name/>
                    <sex/>
                    <date_of_birth/>
                    <parent>
                      <_id/>
                    </parent>
                  </contact>
                </inputs>
                <user_id/>
                <user_phone/>
                <patient_id/>
                <patient_name/>
                <patient_date_of_birth/>
                <patient_age_in_years/>
                <patient_age_in_months/>
                <patient_age_in_days/>
                <patient_sex/>
                <visited_contact_uuid/>
                <household_id/>
                <village_secteur_id/>
                <district_quartier_id/>
                <hospital_id/>
                <commune_id/>
                <prefecture_id/>
                <region_id/>
                <country_id/>
                <vaccine_BCG/>
                <vaccine_VPO_0/>
                <vaccine_PENTA_1/>
                <vaccine_VPO_1/>
                <vaccine_PENTA_2/>
                <vaccine_VPO_2/>
                <vaccine_PENTA_3/>
                <vaccine_VPO_3/>
                <vaccine_VPI_1/>
                <vaccine_VAR_1/>
                <vaccine_VAA/>
                <vaccine_VPI_2/>
                <vaccine_MEN_A/>
                <vaccine_VAR_2/>
                <no_BCG_reason/>
                <no_VPO_0_reason/>
                <no_PENTA_1_reason/>
                <no_VPO_1_reason/>
                <no_PENTA_2_reason/>
                <no_VPO_2_reason/>
                <no_PENTA_3_reason/>
                <no_VPO_3_reason/>
                <no_VPI_1_reason/>
                <no_VAR_1_reason/>
                <no_VAA_reason/>
                <no_VPI_2_reason/>
                <no_MEN_A_reason/>
                <no_VAR_2_reason/>
                <cta_given/>
                <is_birth_vaccine_ok/>
                <is_six_weeks_vaccine_ok/>
                <is_ten_weeks_vaccine_ok/>
                <is_forteen_weeks_vaccine_ok/>
                <is_nine_months_vaccine_ok/>
                <is_fifty_months_vaccine_ok/>
                <is_vaccine_referal/>
                <c_vaccine_status>
                  <c_birth>
                    <c_vaccine_BCG/>
                    <c_no_BCG_reason/>
                    <c_vaccine_VPO_0/>
                    <c_no_VPO_0_reason/>
                  </c_birth>
                  <c_six_weeks>
                    <c_vaccine_PENTA_1/>
                    <c_no_PENTA_1_reason/>
                    <c_vaccine_VPO_1/>
                    <c_no_VPO_1_reason/>
                  </c_six_weeks>
                  <c_ten_weeks>
                    <c_vaccine_PENTA_2/>
                    <c_no_PENTA_2_reason/>
                    <c_vaccine_VPO_2/>
                    <c_no_VPO_2_reason/>
                  </c_ten_weeks>
                  <c_forteen_weeks>
                    <c_vaccine_PENTA_3/>
                    <c_no_PENTA_3_reason/>
                    <c_vaccine_VPO_3/>
                    <c_no_VPO_3_reason/>
                    <c_vaccine_VPI_1/>
                    <c_no_VPI_1_reason/>
                  </c_forteen_weeks>
                  <c_nine_months>
                    <c_vaccine_VAR_1/>
                    <c_no_VAR_1_reason/>
                    <c_vaccine_VAA/>
                    <c_no_VAA_reason/>
                    <c_vaccine_VPI_2/>
                    <c_no_VPI_2_reason/>
                  </c_nine_months>
                  <c_fifty_months>
                    <c_vaccine_MEN_A/>
                    <c_no_MEN_A_reason/>
                    <c_vaccine_VAR_2/>
                    <c_no_VAR_2_reason/>
                  </c_fifty_months>
                </c_vaccine_status>
              </fields>
              <created_by_doc db-doc-ref="/pcimne_register"/>
            </vaccination_followup>
            <vaccination_followup_report_doc db-doc-ref="../vaccination_followup/_id"/>
          </child_vaccination>
          <c_drugs>
            <c_cta_given/>
            <c_reason_cta/>
            <c_quantity_cta_given/>
            <c_amoxicillin_given/>
            <c_reason_amoxicllin/>
            <c_quantity_amoxicillin_given/>
            <c_paracetamol_given/>
            <c_reason_paracetamol/>
            <c_quantity_paracetamol_given/>
            <c_ors_and_zinc_given/>
            <c_quantity_ors_given>0</c_quantity_ors_given>
            <c_quantity_zinc_given>0</c_quantity_zinc_given>
            <c_reason_ors_zinc/>
            <c_mebendazole_given/>
            <c_quantity_mebendazole_given/>
            <c_reason_mebendazole/>
            <c_vitamin_a_given/>
            <c_amount_vitamin_a_given/>
            <c_reason_vit_a/>
            <c_tetracycline_ointment_given/>
            <c_quantity_tetracycline_ointment_given/>
            <c_reason_tetracycline/>
          </c_drugs>
          <group_review>
            <s_summary/>
            <s_patient_info_name/>
            <s_patient_info_sex/>
            <s_patient_info_age/>
            <s_consultation_information/>
            <s_danger_signs_detected/>
            <s_unable_drink_breastfeed/>
            <s_vomits_everything/>
            <s_convulsions/>
            <s_sleepy_unconscious/>
            <s_has_stiff_neck/>
            <s_has_bulging_fontanelle/>
            <s_breathing_difficulty/>
            <s_cough_more_than_14days/>
            <s_subcostal_indrawing/>
            <s_wheezing/>
            <s_bloody_diarrhea/>
            <s_diarrhea_more_than_14_days/>
            <s_blood_in_stool/>
            <s_restless/>
            <s_drinks_hungrily/>
            <s_sunken_eyes/>
            <s_information_on_pathologies/>
            <s_presence_of_fever/>
            <s_presence_of_malaria/>
            <s_presence_of_diarrhea/>
            <s_presence_of_cough_or_cold/>
            <s_presence_of_pneumonia/>
            <s_presence_of_malnutrition/>
            <vaccin_not_up_date/>
            <s_other_diseases_detected/>
            <s_has_afp/>
            <s_has_other_disease_problem/>
            <s_refer_USP/>
            <s_refer_FS_danger_signs/>
            <s_refer_FS_vaccine_status/>
            <s_refer_FS_afp_status/>
            <c_pre_reference_treatments/>
            <s_referal_health_center>others</s_referal_health_center>
            <s_other_referal_health_center/>
            <followup/>
            <s_pcimne_next_visit_date/>
            <s_vaccine_next_visit_date/>
            <s_pfa_next_visit_date/>
            <s_next_visit_no_access/>
          </group_review>
          <meta>
            <instanceID/>
          </meta>
        </pcimne_register>
      </instance>
    <instance id="contact-summary"/>
  </model>

